{
  "version": "0.1",
  "geometries" : {
    "type" : "obj",
    "path" : "./resources/obj_files/table_mug_cup"
  },
  "lights": [
    {
      "light_type": "point",
      "id": "",
      "intensity": 0.1,
      "attenuation": "linear",
      "color": [
        50,
        250,
        300,
        1
      ],
      "transform": {
        "local" : {
          "translate": [
            1,
            1,
            1
          ],
          "scale": [
            1,
            1,
            1
          ],
          "rotate": [
            0,
            0,
            0
          ]
        }
      }
    }
  ],
  "cameras": [
    {
      "camera_type": "standard",
      "id": "camera_01",
      "focal_length": 50.0,
      "aspect_ratio": 1.0,
      "look_at": [
        0.0,
        0.0,
        0.0
      ],
      "transform": {
        "local" : {
          "translate": [
            0,
            0,
            0
          ],
          "scale": [
            1,
            1,
            1
          ],
          "rotate": [
            0,
            0,
            0
          ]
        }
      }
    }
  ],
  "shaders": [
    {
      "shader_type": "lambert",
      "id": "lambert_01",
      "diffuse": [
        50,
        250,
        300,
        1.0
      ]
    }
  ],
  "render_settings":{
    "width": 500,
    "height": 500,
    "ray_samples": 1,
    "shadow_enabled": true,
    "output_dir": "../tmp/output",
    "file_name": "test_{#}",
    "file_ext": ".jpg",
    "camera": "camera_01"
  },
  "misc": {}
}